Workbook

Sheet Dashboard
T1: =MAX(MAX(Income!$A$5:$A$34),MAX(Expenses!$A$5:$A$48)) -> 46105
B2: My Money Dashboard | T2: =DATE(YEAR($T$1),MONTH($T$1),1) -> 46082
B4: =TEXT($T$4,"mmm yyyy")&" to "&TEXT($T$6,"mmm yyyy")&" · last 3 months · all amounts in pesos" -> Jan 2026 to Mar 2026 · last 3 months · all amounts in pesos | T4: =EDATE($T$2,-2) -> 46023
T5: =EDATE($T$2,-1) -> 46054
B6: MONEY IN | E6: MONEY OUT | T6: =EDATE($T$2,0) -> 46082
B7: =SUMIFS(Income!$D$5:$D$34,Income!$A$5:$A$34,">="&$T$4,Income!$A$5:$A$34,"<="&EOMONTH($T$6,0)) -> 55520 | E7: =SUMIFS(Expenses!$D$5:$D$48,Expenses!$A$5:$A$48,">="&$T$4,Expenses!$A$5:$A$48,"<="&EOMONTH($T$6,0)) -> 21579
B10: SAVED | E10: VS BUDGET
B11: =SUMIFS(Income!$D$5:$D$34,Income!$A$5:$A$34,">="&$T$4,Income!$A$5:$A$34,"<="&EOMONTH($T$6,0))-SUMIFS(Expenses!$D$5:$D$48,Expenses!$A$5:$A$48,">="&$T$4,Expenses!$A$5:$A$48,"<="&EOMONTH($T$6,0)) -> 33941 | E11: =(SUM(Budget!$B$5:$B$10)*3)-SUMIFS(Expenses!$D$5:$D$48,Expenses!$A$5:$A$48,">="&$T$4,Expenses!$A$5:$A$48,"<="&EOMONTH($T$6,0)) -> 12621
B14: ="Biggest expense: "&INDEX($B$19:$B$24,MATCH(MAX($C$19:$C$24),$C$19:$C$24,0))&" ("&TEXT(MAX($C$19:$C$24),"₱#,##0")&", "&TEXT(MAX($C$19:$C$24)/SUMIFS(Expenses!$D$5:$D$48,Expenses!$A$5:$A$48,">="&$T$4,Expenses!$A$5:$A$48,"<="&EOMONTH($T$6,0)),"0%")&" of spending). You kept "&TEXT(IFERROR((SUMIFS(Income!$D$5:$D$34,Income!$A$5:$A$34,">="&$T$4,Income!$A$5:$A$34,"<="&EOMONTH($T$6,0))-SUMIFS(Expenses!$D$5:$D$48,Expenses!$A$5:$A$48,">="&$T$4,Expenses!$A$5:$A$48,"<="&EOMONTH($T$6,0)))/SUMIFS(Income!$D$5:$D$34,Income!$A$5:$A$34,">="&$T$4,Income!$A$5:$A$34,"<="&EOMONTH($T$6,0)),0),"0%")&" of what you earned." -> Biggest expense: Living Expenses (₱16,180, 75% of spending). You kept 61% of what you earned.
B17: Where the money went
B18: Category | C18: Spent | D18: Budget | E18: Left over | F18: % of spending
B19: Living Expenses | C19: =SUMIFS(Expenses!$D$5:$D$48,Expenses!$B$5:$B$48,B19,Expenses!$A$5:$A$48,">="&$T$4,Expenses!$A$5:$A$48,"<="&EOMONTH($T$6,0)) -> 16180 | D19: =IFERROR(INDEX(Budget!$B$5:$B$10,MATCH(B19,Budget!$A$5:$A$10,0))*3,0) -> 19500 | E19: =D19-C19 -> 3320 | F19: =IFERROR(C19/SUMIFS(Expenses!$D$5:$D$48,Expenses!$A$5:$A$48,">="&$T$4,Expenses!$A$5:$A$48,"<="&EOMONTH($T$6,0)),0) -> 0.74980305
B20: Dining Out | C20: =SUMIFS(Expenses!$D$5:$D$48,Expenses!$B$5:$B$48,B20,Expenses!$A$5:$A$48,">="&$T$4,Expenses!$A$5:$A$48,"<="&EOMONTH($T$6,0)) -> 1170 | D20: =IFERROR(INDEX(Budget!$B$5:$B$10,MATCH(B20,Budget!$A$5:$A$10,0))*3,0) -> 3000 | E20: =D20-C20 -> 1830 | F20: =IFERROR(C20/SUMIFS(Expenses!$D$5:$D$48,Expenses!$A$5:$A$48,">="&$T$4,Expenses!$A$5:$A$48,"<="&EOMONTH($T$6,0)),0) -> 0.05421938
B21: Transport | C21: =SUMIFS(Expenses!$D$5:$D$48,Expenses!$B$5:$B$48,B21,Expenses!$A$5:$A$48,">="&$T$4,Expenses!$A$5:$A$48,"<="&EOMONTH($T$6,0)) -> 1510 | D21: =IFERROR(INDEX(Budget!$B$5:$B$10,MATCH(B21,Budget!$A$5:$A$10,0))*3,0) -> 3600 | E21: =D21-C21 -> 2090 | F21: =IFERROR(C21/SUMIFS(Expenses!$D$5:$D$48,Expenses!$A$5:$A$48,">="&$T$4,Expenses!$A$5:$A$48,"<="&EOMONTH($T$6,0)),0) -> 0.069975439
B22: Discretionary | C22: =SUMIFS(Expenses!$D$5:$D$48,Expenses!$B$5:$B$48,B22,Expenses!$A$5:$A$48,">="&$T$4,Expenses!$A$5:$A$48,"<="&EOMONTH($T$6,0)) -> 1799 | D22: =IFERROR(INDEX(Budget!$B$5:$B$10,MATCH(B22,Budget!$A$5:$A$10,0))*3,0) -> 4500 | E22: =D22-C22 -> 2701 | F22: =IFERROR(C22/SUMIFS(Expenses!$D$5:$D$48,Expenses!$A$5:$A$48,">="&$T$4,Expenses!$A$5:$A$48,"<="&EOMONTH($T$6,0)),0) -> 0.083368089
B23: Medical | C23: =SUMIFS(Expenses!$D$5:$D$48,Expenses!$B$5:$B$48,B23,Expenses!$A$5:$A$48,">="&$T$4,Expenses!$A$5:$A$48,"<="&EOMONTH($T$6,0)) -> 620 | D23: =IFERROR(INDEX(Budget!$B$5:$B$10,MATCH(B23,Budget!$A$5:$A$10,0))*3,0) -> 2400 | E23: =D23-C23 -> 1780 | F23: =IFERROR(C23/SUMIFS(Expenses!$D$5:$D$48,Expenses!$A$5:$A$48,">="&$T$4,Expenses!$A$5:$A$48,"<="&EOMONTH($T$6,0)),0) -> 0.028731637
B24: Charity | C24: =SUMIFS(Expenses!$D$5:$D$48,Expenses!$B$5:$B$48,B24,Expenses!$A$5:$A$48,">="&$T$4,Expenses!$A$5:$A$48,"<="&EOMONTH($T$6,0)) -> 300 | D24: =IFERROR(INDEX(Budget!$B$5:$B$10,MATCH(B24,Budget!$A$5:$A$10,0))*3,0) -> 1200 | E24: =D24-C24 -> 900 | F24: =IFERROR(C24/SUMIFS(Expenses!$D$5:$D$48,Expenses!$A$5:$A$48,">="&$T$4,Expenses!$A$5:$A$48,"<="&EOMONTH($T$6,0)),0) -> 0.013902405
B25: Total | C25: =SUM(C19:C24) -> 21579 | D25: =SUM(D19:D24) -> 34200 | E25: =SUM(E19:E24) -> 12621 | F25: =IFERROR(C25/SUMIFS(Expenses!$D$5:$D$48,Expenses!$A$5:$A$48,">="&$T$4,Expenses!$A$5:$A$48,"<="&EOMONTH($T$6,0)),0) -> 1
B27: Month by month
B28: Month | C28: Money In | D28: Money Out | E28: Saved
B29: =TEXT($T$4,"mmm yyyy") -> Jan 2026 | C29: =SUMIFS(Income!$D$5:$D$34,Income!$A$5:$A$34,">="&$T$4,Income!$A$5:$A$34,"<="&EOMONTH($T$4,0)) -> 18120 | D29: =SUMIFS(Expenses!$D$5:$D$48,Expenses!$A$5:$A$48,">="&$T$4,Expenses!$A$5:$A$48,"<="&EOMONTH($T$4,0)) -> 8230 | E29: =C29-D29 -> 9890
B30: =TEXT($T$5,"mmm yyyy") -> Feb 2026 | C30: =SUMIFS(Income!$D$5:$D$34,Income!$A$5:$A$34,">="&$T$5,Income!$A$5:$A$34,"<="&EOMONTH($T$5,0)) -> 18900 | D30: =SUMIFS(Expenses!$D$5:$D$48,Expenses!$A$5:$A$48,">="&$T$5,Expenses!$A$5:$A$48,"<="&EOMONTH($T$5,0)) -> 6890 | E30: =C30-D30 -> 12010
B31: =TEXT($T$6,"mmm yyyy") -> Mar 2026 | C31: =SUMIFS(Income!$D$5:$D$34,Income!$A$5:$A$34,">="&$T$6,Income!$A$5:$A$34,"<="&EOMONTH($T$6,0)) -> 18500 | D31: =SUMIFS(Expenses!$D$5:$D$48,Expenses!$A$5:$A$48,">="&$T$6,Expenses!$A$5:$A$48,"<="&EOMONTH($T$6,0)) -> 6459 | E31: =C31-D31 -> 12041

Sheet Sheet

Sheet Income
A1: Income Log
A2: Add one row each time you receive money. The dashboard updates itself.
A4: Date | B4: Source | C4: Description | D4: Amount
A5: 45976 | B5: Salary | C5: Monthly salary | D5: 18000
A6: 46006 | B6: Salary | C6: Monthly salary | D6: 18000
A7: 46037 | B7: Salary | C7: Monthly salary | D7: 18120
A8: 46068 | B8: Salary | C8: Monthly salary | D8: 18450
A9: 46081 | B9: Dividends | C9: Investment dividend | D9: 450
A10: 46096 | B10: Salary | C10: Monthly salary | D10: 18500

Sheet Expenses
A1: Expense Log
A2: Add one row each time you spend. Category and Payment Method are dropdowns.
A4: Date | B4: Category | C4: Description | D4: Amount | E4: Payment Method
A5: 45966 | B5: Living Expenses | C5: Room rent | D5: 5000 | E5: Bank Transfer
A6: 45996 | B6: Living Expenses | C6: Room rent | D6: 5000 | E6: Bank Transfer
A7: 46027 | B7: Living Expenses | C7: Room rent | D7: 5000 | E7: Bank Transfer
A8: 46030 | B8: Living Expenses | C8: Meralco electric bill | D8: 1180 | E8: Bank Transfer
A9: 46034 | B9: Dining Out | C9: Lunch with officemates | D9: 320 | E9: Cash
A10: 46040 | B10: Transport | C10: Grab to work | D10: 480 | E10: GCash
A11: 46044 | B11: Discretionary | C11: Shopee order | D11: 1250 | E11: GCash
A12: 46058 | B12: Living Expenses | C12: Room rent | D12: 5000 | E12: Bank Transfer
A13: 46063 | B13: Medical | C13: Vitamins & meds | D13: 620 | E13: Cash
A14: 46069 | B14: Dining Out | C14: Dinner out | D14: 450 | E14: GCash
A15: 46073 | B15: Transport | C15: Grab to work | D15: 520 | E15: GCash
A16: 46078 | B16: Charity | C16: Church donation | D16: 300 | E16: Cash
... A20: 46105 | B20: Transport | C20: Grab to work | D20: 510 | E20: GCash

Sheet Budget
A1: Monthly Budget
A2: Set how much you plan to spend per month in each category. Edit the blue column only.
A4: Category | B4: Monthly Budget
A5: Living Expenses | B5: 6500
A6: Dining Out | B6: 1000
A7: Transport | B7: 1200
A8: Discretionary | B8: 1500
A9: Medical | B9: 800
A10: Charity | B10: 400
A11: Total per month | B11: =SUM(B5:B10) -> 11400
